whatsapp_manager/__init__.py
whatsapp_manager-0.0.1.dist-info/licenses/LICENSE
whatsapp_manager-0.0.1.dist-info/METADATA
whatsapp_manager-0.0.1.dist-info/WHEEL
whatsapp_manager-0.0.1.dist-info/top_level.txt
whatsapp_manager-0.0.1.dist-info/RECORD
