Metadata-Version: 2.4
Name: whatsapp-manager
Version: 0.0.1
Summary: A Python wrapper for Facebook and WhatsApp API useful endpoints
Author-email: Francisco <francisco@maxilarlabs.com>
License-Expression: MIT
Project-URL: Homepage, https://github.com/doasfrancisco/whatsapp-api
Project-URL: Issues, https://github.com/doasfrancisco/whatsapp-api/issues
Classifier: Programming Language :: Python :: 3
Classifier: Operating System :: OS Independent
Requires-Python: >=3.11
License-File: LICENSE
Requires-Dist: certifi==2024.12.14
Requires-Dist: charset-normalizer==3.4.1
Requires-Dist: idna==3.10
Requires-Dist: python-dotenv==1.0.1
Requires-Dist: requests==2.32.3
Requires-Dist: urllib3==2.3.0
Dynamic: license-file
